cf_compare_versions-0.0.1.dist-info/DESCRIPTION.rst
cf_compare_versions-0.0.1.dist-info/METADATA
cf_compare_versions-0.0.1.dist-info/RECORD
cf_compare_versions-0.0.1.dist-info/WHEEL
cf_compare_versions-0.0.1.dist-info/metadata.json
cf_compare_versions-0.0.1.dist-info/top_level.txt
compare_versions/__init__.py
compare_versions/compare_versions.py
