Metadata-Version: 2.0
Name: cf-compare-versions
Version: 0.0.1
Summary: Compare version strings
Home-page: https://github.com/carlos-ferras/code-challenge/compare_versions
Author: Carlos Ferras
Author-email: c4rlos.ferra5@gmail.com
License: MIT
Platform: UNKNOWN
